{
  "id": "2025-02-09T19-10-00-001",
  "slug": "ac-temperature-confusion",
  "event_datetime": "2025-02-09T19:10:00+08:00",
  "title_zh": "車內冷氣怎麼調？",
  "short_sentence_zh": "她不知道冷氣模式會影響溫度設定。",
  "summary_zh": "梅無法理解「風量模式」與「冷氣模式」的差別，導致她一直調不到想要的溫度。此事件反映執行功能下降，特別是在多步驟操作與因果理解上。",
  "tags": [
    "執行功能障礙",
    "器物操作困難"
  ],
  "photos": [
    "/images/cases/ac-temperature-confusion/02.jpg"
  ],
  "recorded_at": "2025-02-09T19:10:00+08:00",
  "title": {
    "zh": "車內冷氣怎麼調？",
    "en": null
  },
  "short_sentence": {
    "zh": "車內冷氣怎麼調？",
    "en": null
  },
  "summary": {
    "zh": "無法理解「風量模式」與「冷氣模式」的差別，導致她一直調不到想要的溫度。此事件反映執行功能下降，特別是在多步驟操作與因果理解上。",
    "en": null
  },
  "full_story": {
    "zh": "",
    "en": null
  },
  "attachments": [],
  "created_at": "2025-02-09T19:10:00+08:00",
  "updated_at": "2025-12-07T09:16:59.279Z",
  "data_version": 3
}